{
  "adventureProgress": {
    "1": {
      "adventure": "402",
      "id": "1",
      "progress": "100"
    },
    "2": {
      "adventure": "401",
      "id": "2",
      "progress": "400"
    },
    "3": {
      "adventure": "",
      "id": "3",
      "progress": "800"
    },
    "4": {
      "adventure": "",
      "id": "4",
      "progress": "1000"
    },
    "5": {
      "adventure": "",
      "id": "5",
      "progress": "1500"
    },
    "6": {
      "adventure": "",
      "id": "6",
      "progress": "1800"
    }
  }
}